ztoolacdc/__init__.py
ztoolacdc/create_freq.py
ztoolacdc/frame_conversion.py
ztoolacdc/frequency_sweep.py
ztoolacdc/read_admittance.py
ztoolacdc/read_and_save.py
ztoolacdc/stability.py
ztoolacdc/yz_computation.py
ztoolacdc/Scan/Z_tool.bakx
ztoolacdc/Scan/Z_tool.pslx
ztoolacdc/Scan/Z_tool.psmx
ztoolacdc/Scan/Z_tool.gf46/Z_tool.mak
ztoolacdc-0.1.28.dist-info/licenses/LICENSE.md
ztoolacdc-0.1.28.dist-info/METADATA
ztoolacdc-0.1.28.dist-info/WHEEL
ztoolacdc-0.1.28.dist-info/top_level.txt
ztoolacdc-0.1.28.dist-info/RECORD
