Metadata-Version: 2.4
Name: ztoolacdc
Version: 0.1.28
Summary: Frequency domain small-signal analysis toolbox for EMT models
Author-email: Francisco Javier Cifuentes Garcia <franciscojavier.cifuentesgarcia@kuleuven.be>
License: GNU GPL v3
Project-URL: Homepage, https://www.esat.kuleuven.be/electa/ztool
Project-URL: Documentation, https://www.esat.kuleuven.be/electa/ztool
Keywords: stability,frequency,admittance,impedance,scan,PSCAD
Classifier: License :: OSI Approved :: GNU General Public License v3 (GPLv3)
Classifier: Natural Language :: English
Classifier: Operating System :: Microsoft :: Windows
Classifier: Programming Language :: Python :: 3.10
Classifier: Topic :: Scientific/Engineering
Requires-Python: >=3.7
License-File: LICENSE.md
Requires-Dist: numpy>=1.20.0
Requires-Dist: matplotlib>=3.5
Requires-Dist: scipy>=1.7
Requires-Dist: mhi-pscad>=2.9.0
Dynamic: license-file
